wdtqm/__init__.py
wdtqm-0.0.4.dist-info/METADATA
wdtqm-0.0.4.dist-info/WHEEL
wdtqm-0.0.4.dist-info/RECORD
